rez_tools/__init__.py
rez_tools/__main__.py
rez_tools/cli.py
rez_tools/plugin.py
rez_tools/reztoolsconfig.py
rez_tools/template.py
rez_tools/test/__init__.py
rez_tools-0.3.0.dist-info/LICENSE
rez_tools-0.3.0.dist-info/METADATA
rez_tools-0.3.0.dist-info/WHEEL
rez_tools-0.3.0.dist-info/entry_points.txt
rez_tools-0.3.0.dist-info/top_level.txt
rez_tools-0.3.0.dist-info/RECORD
