Metadata-Version: 2.1
Name: rez-tools
Version: 0.3.0
Summary: A suite tool command line for rez.
Home-page: https://github.com/loonghao/rez-tools
Author: Long Hao
Author-email: hal.long@outlook.com
License: MIT
Platform: UNKNOWN
Classifier: Development Status :: 4 - Beta
Classifier: License :: OSI Approved :: MIT License
Classifier: Intended Audience :: Developers
Classifier: Programming Language :: Python
Classifier: Programming Language :: Python :: 2
Classifier: Programming Language :: Python :: 2.7
Classifier: Programming Language :: Python :: 3.5
Classifier: Programming Language :: Python :: 3.6
Classifier: Programming Language :: Python :: 3.7
Classifier: Programming Language :: Python :: 3.8
Requires-Dist: click (>=7.0)
Requires-Dist: pyyaml (>=5.0)
